README.md
setup.py
mute_tf_warnings/__init__.py
mute_tf_warnings.egg-info/PKG-INFO
mute_tf_warnings.egg-info/SOURCES.txt
mute_tf_warnings.egg-info/dependency_links.txt
mute_tf_warnings.egg-info/not-zip-safe
mute_tf_warnings.egg-info/top_level.txt