Metadata-Version: 2.1
Name: mute-tf-warnings
Version: 0.11
Summary: a package for allocating tensorflow gpu memory use in python
Home-page: https://github.com/kongkip/mute_tf_warnings
Author: Evans Kiplagat
Author-email: evanskiplagat3@gmail.com
License: MIT
Platform: UNKNOWN
